tpds/__init__.py
tpds/api/__init__.py
tpds/api/core.py
tpds/api/loader.py
tpds/api/api/__init__.py
tpds/api/api/demos.py
tpds/api/api/router.py
tpds/api/api/usecases.py
tpds/api/api/hw/__init__.py
tpds/api/api/hw/api_board.py
tpds/api/api/hw/api_device.py
tpds/api/api/manifest_file/api_manifest.py
tpds/api/api/manifest_file/MCHP_manifest_signer/MCHP_manifest_signer_1_Jan2019_July2019.crt
tpds/api/api/manifest_file/MCHP_manifest_signer/MCHP_manifest_signer_2_Aug2019_Aug2020.crt
tpds/api/api/manifest_file/MCHP_manifest_signer/MCHP_manifest_signer_3_Aug-13-2020-Aug-13-2023.crt
tpds/api/api/package_manager/api_package_manager.py
tpds/api/api/schemas/__init__.py
tpds/api/api/schemas/hw.py
tpds/api/assets/favicon.ico
tpds/configurator/__init__.py
tpds/configurator/algorithms.py
tpds/configurator/api.py
tpds/configurator/configurator.py
tpds/configurator/models.py
tpds/configurator/store.py
tpds/configurator/engine/__init__.py
tpds/configurator/engine/engine.py
tpds/configurator/engine/exceptions.py
tpds/configurator/engine/rule.py
tpds/configurator/engine/state.py
tpds/configurator/engine/types.py
tpds/devices/__init__.py
tpds/devices/boards_schema.yaml
tpds/devices/devices_schema.yaml
tpds/devices/tpds_boards.py
tpds/devices/tpds_devices.py
tpds/devices/tpds_models.py
tpds/devices/data/ecc608-tcsm.yaml
tpds/devices/data/ecc608-tflx.yaml
tpds/devices/data/ecc608-tng.yaml
tpds/devices/data/modules.yaml
tpds/devices/data/sha204.yaml
tpds/devices/data/ta100.yaml
tpds/helper/__init__.py
tpds/helper/logger.py
tpds/helper/processing.py
tpds/helper/singleton.py
tpds/helper/utils.py
tpds/launcher/__init__.py
tpds/launcher/start.py
tpds/package_manager/__init__.py
tpds/package_manager/client_model.py
tpds/package_manager/data_models.py
tpds/package_manager/manager.py
tpds/package_manager/packages_schema.yaml
tpds/package_manager/pip_client.py
tpds/package_manager/licenses/mchp.txt
tpds/servers/TPDS_notebook_config.py
tpds/servers/__init__.py
tpds/servers/jupyter_server.py
tpds_core-2.4.2.dist-info/licenses/LICENSE
tpds_core-2.4.2.dist-info/METADATA
tpds_core-2.4.2.dist-info/WHEEL
tpds_core-2.4.2.dist-info/entry_points.txt
tpds_core-2.4.2.dist-info/top_level.txt
tpds_core-2.4.2.dist-info/RECORD
