Metadata-Version: 2.4
Name: tpds-core
Version: 2.4.2
Summary: Microchip(SPG) Trust Platform Core 
Maintainer-email: Microchip Technology <SPG.Tools@microchip.com>
License: (c) 2015-2025 Microchip Technology Inc. and its subsidiaries.
Classifier: License :: Other/Proprietary License
Classifier: Development Status :: 4 - Beta
Classifier: Programming Language :: Python :: 3
Classifier: Operating System :: OS Independent
Requires-Python: >=3.8
License-File: LICENSE
Requires-Dist: asn1crypto
Requires-Dist: beautifulsoup4
Requires-Dist: deepdiff
Requires-Dist: cryptography~=35.0.0
Requires-Dist: python-multipart
Requires-Dist: fastapi
Requires-Dist: jsonschema
Requires-Dist: Markdown
Requires-Dist: packaging
Requires-Dist: psutil
Requires-Dist: pydantic<2.0
Requires-Dist: pymcuprog
Requires-Dist: pyusb
Requires-Dist: PyYAML
Requires-Dist: starlette
Requires-Dist: tabulate
Requires-Dist: uvicorn
Requires-Dist: jupyter_client==7.4.1
Requires-Dist: jupyter_core==5.3.1
Requires-Dist: jupyter-server==1.24.0
Requires-Dist: jupyterlab-pygments==0.2.2
Requires-Dist: jupyterlab_server==2.24.0
Requires-Dist: jupyterlab-widgets==3.0.8
Requires-Dist: traitlets==5.9.0
Requires-Dist: notebook<7,>=6.4.12
Requires-Dist: nbclient==0.7.4
Requires-Dist: nbconvert==7.7.4
Requires-Dist: voila==0.4.0
Requires-Dist: cryptoauthlib>=20241015
Requires-Dist: tpds-application-root
Requires-Dist: tpds-boards
Requires-Dist: tpds-manifest
Requires-Dist: tpds-helper>=2.3.10
Requires-Dist: tpds-voila-template
Requires-Dist: tpds-device-manifest
Provides-Extra: dev
Requires-Dist: flake8; extra == "dev"
Requires-Dist: black; extra == "dev"
Requires-Dist: isort; extra == "dev"
Requires-Dist: mypy; extra == "dev"
Provides-Extra: test
Requires-Dist: httpx; extra == "test"
Requires-Dist: responses==0.23.1; extra == "test"
Requires-Dist: prompt-toolkit==3.0.41; extra == "test"
Requires-Dist: pytest-cov; extra == "test"
Requires-Dist: pytest-mock; extra == "test"
Requires-Dist: pytest-integration; extra == "test"
Dynamic: license-file
